HW3/ALU.v
module ALU(
    input  [31:0] data1_i,
    input  [31:0] data2_i,
    input  [2:0]  ALUCtrl_i,
    output reg [31:0] data_o,
    output zero_o
);

    // Temporary 33-bit wire for addition/subtraction to detect overflow
    wire [32:0] temp_add;
    wire [32:0] temp_sub;
    
    // Calculate addition and subtraction with extra bit
    assign temp_add = {1'b0, data1_i} + {1'b0, data2_i};
    assign temp_sub = {1'b0, data1_i} - {1'b0, data2_i};

    // Zero flag is high when output is zero
    assign zero_o = (data_o == 32'b0);

    // ALU operations
    always @(*) begin
        case (ALUCtrl_i)
            3'b000: data_o = temp_add[31:0];          // Addition with wrap-around
            3'b001: data_o = temp_sub[31:0];          // Subtraction with wrap-around
            3'b010: data_o = data1_i & data2_i;          // Bitwise AND
            3'b011: data_o = data1_i | data2_i;          // Bitwise OR
            3'b100: data_o = data1_i ^ data2_i;          // Bitwise XOR
            3'b101: data_o = data1_i << data2_i[4:0];    // Left Shift
            3'b110: data_o = $signed(data1_i) >>> data2_i[4:0];  // Arithmetic Right Shift
            3'b111: data_o = data1_i >> data2_i[4:0];    // Logical Right Shift
            default: data_o = 32'b0;
        endcase
    end

endmodule

HW3/ALU_tb.v
module ALU_tb;
    reg  [31:0] data1_i;
    reg  [31:0] data2_i;
    reg  [2:0]  ALUCtrl_i;
    wire [31:0] data_o;
    wire zero_o;

    // Instantiate the ALU
    ALU alu(
        .data1_i(data1_i),
        .data2_i(data2_i),
        .ALUCtrl_i(ALUCtrl_i),
        .data_o(data_o),
        .zero_o(zero_o)
    );

    // For printing test results
    reg [255:0] op_name;
    always @(*) begin
        case(ALUCtrl_i)
            3'b000: op_name = "ADD";
            3'b001: op_name = "SUB";
            3'b010: op_name = "AND";
            3'b011: op_name = "OR";
            3'b100: op_name = "XOR";
            3'b101: op_name = "SLL";
            3'b110: op_name = "SRA";
            3'b111: op_name = "SRL";
            default: op_name = "UNKNOWN";
        endcase
    end

    // Test vectors
    initial begin
        $dumpfile("ALU.vcd");
        $dumpvars(0, ALU_tb);
        
        // Test 1: Basic arithmetic operations
        data1_i = 32'h00000005; data2_i = 32'h00000003;

        //data1_i = 32'hFFFFFFFA;
        //data2_i = 32'h0000000A;
        // Addition
        ALUCtrl_i = 3'b000;
        #10;
        if(data_o !== 32'h00000008) $display("Error: ADD failed");

        else $display("Test ADD passed: %h + %h = %h", data1_i, data2_i, data_o);
        
        // Subtraction
        ALUCtrl_i = 3'b001;
        #10;
        if(data_o !== 32'h00000002) $display("Error: SUB failed");
        else $display("Test SUB passed: %h - %h = %h", data1_i, data2_i, data_o);

        // Test 2: Logical operations
        data1_i = 32'hF0F0F0F0; data2_i = 32'h0F0F0F0F;
        
        // AND
        ALUCtrl_i = 3'b010;
        #10;
        if(data_o !== 32'h00000000) $display("Error: AND failed");
        else $display("Test AND passed: %h & %h = %h", data1_i, data2_i, data_o);
        
        // OR
        ALUCtrl_i = 3'b011;
        #10;
        if(data_o !== 32'hFFFFFFFF) $display("Error: OR failed");
        else $display("Test OR passed: %h | %h = %h", data1_i, data2_i, data_o);
        
        // XOR
        ALUCtrl_i = 3'b100;
        #10;
        if(data_o !== 32'hFFFFFFFF) $display("Error: XOR failed");
        else $display("Test XOR passed: %h ^ %h = %h", data1_i, data2_i, data_o);

        // Test 3: Shift operations
        data1_i = 32'h0000FFFF; data2_i = 32'h00000004;
        
        // Logical left shift
        ALUCtrl_i = 3'b101;
        #10;
        if(data_o !== 32'h000FFFF0) $display("Error: SLL failed");
        else $display("Test SLL passed: %h << %h = %h", data1_i, data2_i[4:0], data_o);
        
        // Arithmetic right shift
        data1_i = 32'h80000000;
        ALUCtrl_i = 3'b110;
        #10;
        if(data_o !== 32'hF8000000) $display("Error: SRA failed");
        else $display("Test SRA passed: %h >>> %h = %h", data1_i, data2_i[4:0], data_o);
        
        // Logical right shift
        ALUCtrl_i = 3'b111;
        #10;
        if(data_o !== 32'h08000000) $display("Error: SRL failed");
        else $display("Test SRL passed: %h >> %h = %h", data1_i, data2_i[4:0], data_o);

        // Test 4: Overflow test for addition
        data1_i = 32'hFFFFFFFF; data2_i = 32'h00000001;
        ALUCtrl_i = 3'b000;
        #10;
        if(data_o !== 32'h00000000) $display("Error: ADD overflow failed");
        else $display("Test ADD overflow passed: %h + %h = %h", data1_i, data2_i, data_o);

        // Test 5: Underflow test for subtraction
        data1_i = 32'h00000000; data2_i = 32'h00000001;
        ALUCtrl_i = 3'b001;
        #10;
        if(data_o !== 32'hFFFFFFFF) $display("Error: SUB underflow failed");
        else $display("Test SUB underflow passed: %h - %h = %h", data1_i, data2_i, data_o);

        // Test 6: Zero flag test
        data1_i = 32'h00000000; data2_i = 32'h00000000;
        ALUCtrl_i = 3'b000;
        #10;
        if(!zero_o) $display("Error: Zero flag failed");
        else $display("Test zero flag passed");

        $finish;
    end
endmodule

HW3/ALU.vcd
$date
	Sat Nov 16 02:06:05 2024
$end
$version
	Icarus Verilog
$end
$timescale
	1s
$end
$scope module ALU_tb $end
$var wire 1 ! zero_o $end
$var wire 32 " data_o [31:0] $end
$var reg 3 # ALUCtrl_i [2:0] $end
$var reg 32 $ data1_i [31:0] $end
$var reg 32 % data2_i [31:0] $end
$var reg 256 & op_name [255:0] $end
$scope module alu $end
$var wire 3 ' ALUCtrl_i [2:0] $end
$var wire 32 ( data1_i [31:0] $end
$var wire 32 ) data2_i [31:0] $end
$var wire 1 ! zero_o $end
$var wire 33 * temp_sub [32:0] $end
$var wire 33 + temp_add [32:0] $end
$var reg 32 , data_o [31:0] $end
$upscope $end
$upscope $end
$enddefinitions $end
$comment Show the parameter values. $end
$dumpall
$end
#0
$dumpvars
b1000 ,
b1000 +
b10 *
b11 )
b101 (
b0 '
b10000010100010001000100 &
b11 %
b101 $
b0 #
b1000 "
0!
$end
#10
b10 "
b10 ,
b10100110101010101000010 &
b1 #
b1 '
#20
b10000010100111001000100 &
1!
b0 "
b0 ,
b10 #
b10 '
b1111000011110000111100001111 %
b1111000011110000111100001111 )
b11111111111111111111111111111111 +
b11100001111000011110000111100001 *
b11110000111100001111000011110000 $
b11110000111100001111000011110000 (
#30
0!
b11111111111111111111111111111111 "
b11111111111111111111111111111111 ,
b100111101010010 &
b11 #
b11 '
#40
b10110000100111101010010 &
b100 #
b100 '
#50
b10100110100110001001100 &
b11111111111111110000 "
b11111111111111110000 ,
b101 #
b101 '
b100 %
b100 )
b10000000000000011 +
b1111111111111011 *
b1111111111111111 $
b1111111111111111 (
#60
b10100110101001001000001 &
b11111000000000000000000000000000 "
b11111000000000000000000000000000 ,
b110 #
b110 '
b10000000000000000000000000000100 +
b1111111111111111111111111111100 *
b10000000000000000000000000000000 $
b10000000000000000000000000000000 (
#70
b1000000000000000000000000000 "
b1000000000000000000000000000 ,
b10100110101001001001100 &
b111 #
b111 '
#80
b10000010100010001000100 &
1!
b0 "
b0 ,
b0 #
b0 '
b1 %
b1 )
b100000000000000000000000000000000 +
b11111111111111111111111111111110 *
b11111111111111111111111111111111 $
b11111111111111111111111111111111 (
#90
b10100110101010101000010 &
0!
b11111111111111111111111111111111 "
b11111111111111111111111111111111 ,
b1 #
b1 '
b1 +
b111111111111111111111111111111111 *
b0 $
b0 (
#100
b10000010100010001000100 &
1!
b0 "
b0 ,
b0 #
b0 '
b0 +
b0 *
b0 %
b0 )
