HW3/Registers.v
module Registers(
    input         clk_i,
    input  [4:0]  RS1addr_i,
    input  [4:0]  RS2addr_i,
    input  [4:0]  RDaddr_i,
    input  [31:0] RDdata_i,
    input         RegWrite_i,
    output [31:0] RS1data_o,
    output [31:0] RS2data_o
);

    // Register file
    reg [31:0] registers [0:31];
    integer i;

    // Initialize all registers to 0
    initial begin
        for (i = 0; i < 32; i = i + 1) begin
            registers[i] = 32'b0;
        end
    end
   

    // Read data
    assign RS1data_o = (RS1addr_i == 5'b0) ? 32'b0 : registers[RS1addr_i];
    assign RS2data_o = (RS2addr_i == 5'b0) ? 32'b0 : registers[RS2addr_i];

    // Write data
    always @(posedge clk_i) begin
        if (RegWrite_i && RDaddr_i != 5'b0) begin
            registers[RDaddr_i] <= RDdata_i;
        end
    end

endmodule

HW3/Registers_tb.v
module Registers_tb;
    reg         clk_i;
    reg  [4:0]  RS1addr_i;
    reg  [4:0]  RS2addr_i;
    reg  [4:0]  RDaddr_i;
    reg  [31:0] RDdata_i;
    reg         RegWrite_i;
    wire [31:0] RS1data_o;
    wire [31:0] RS2data_o;

    // Instantiate the register file
    Registers regs(
        .clk_i(clk_i),
        .RS1addr_i(RS1addr_i),
        .RS2addr_i(RS2addr_i),
        .RDaddr_i(RDaddr_i),
        .RDdata_i(RDdata_i),
        .RegWrite_i(RegWrite_i),
        .RS1data_o(RS1data_o),
        .RS2data_o(RS2data_o)
    );

    // Clock generation
    initial begin
        clk_i = 0;
        forever #5 clk_i = ~clk_i;
    end

    // Test procedure
    initial begin
        $dumpfile("Registers.vcd");
        $dumpvars(0, Registers_tb);
        
        // Initialize signals
        RS1addr_i = 0;
        RS2addr_i = 0;
        RDaddr_i = 0;
        RDdata_i = 0;
        RegWrite_i = 0;
        #10;

        // Test 1: Write to register 0 (should remain 0)
        RegWrite_i = 1;
        RDaddr_i = 0;
        RDdata_i = 32'hFFFFFFFF;
        #10;
        
        RS1addr_i = 0;
        RegWrite_i = 0;
        #10;
        if(RS1data_o !== 32'h0) 
            $display("Error: Register 0 was modified");
        else 
            $display("Test 1 passed: Register 0 remains 0");

        // Test 2: Write and read from a regular register
        RegWrite_i = 1;
        RDaddr_i = 5'd1;
        RDdata_i = 32'h12345678;
        #10;
        
        RS1addr_i = 5'd1;
        RegWrite_i = 0;
        #10;
        if(RS1data_o !== 32'h12345678)
            $display("Error: Write/Read to register 1 failed");
        else
            $display("Test 2 passed: Write/Read to register 1 successful");

        // Test 3: Simultaneous read from two different registers
        RegWrite_i = 1;
        RDaddr_i = 5'd2;
        RDdata_i = 32'h87654321;
        #10;
        
        RS1addr_i = 5'd1;
        RS2addr_i = 5'd2;
        RegWrite_i = 0;
        #10;
        if(RS1data_o !== 32'h12345678 || RS2data_o !== 32'h87654321)
            $display("Error: Simultaneous read failed");
        else
            $display("Test 3 passed: Simultaneous read successful");

        // Test 4: Write enable functionality
        RegWrite_i = 0;
        RDaddr_i = 5'd1;
        RDdata_i = 32'hAAAAAAAA;
        #10;
        
        RS1addr_i = 5'd1;
        #10;
        if(RS1data_o !== 32'h12345678)
            $display("Error: Write occurred when RegWrite_i was 0");
        else
            $display("Test 4 passed: Write disabled when RegWrite_i = 0");

        // Test 5: Read during write
        RegWrite_i = 1;
        RDaddr_i = 5'd3;
        RDdata_i = 32'hBBBBBBBB;
        RS1addr_i = 5'd3;
        #1;  // Check value before clock edge
        if(RS1data_o !== 32'h0)
            $display("Error: Register 3 should be 0 before write, but got %h", RS1data_o);
        else
            $display("Test 5.1 passed: Register 3 is 0 before write");
        #9;  // Wait for clock edge and check again
        if(RS1data_o !== 32'hBBBBBBBB)
            $display("Error: Read wrong value after write");
        else
            $display("Test 5.2 passed: Read during write successful");

        $finish;
    end
endmodule

HW3/Registers.vcd
$date
	Sun Nov 10 00:11:03 2024
$end
$version
	Icarus Verilog
$end
$timescale
	1s
$end
$scope module Registers_tb $end
$var wire 32 ! RS2data_o [31:0] $end
$var wire 32 " RS1data_o [31:0] $end
$var reg 5 # RDaddr_i [4:0] $end
$var reg 32 $ RDdata_i [31:0] $end
$var reg 5 % RS1addr_i [4:0] $end
$var reg 5 & RS2addr_i [4:0] $end
$var reg 1 ' RegWrite_i $end
$var reg 1 ( clk_i $end
$scope module regs $end
$var wire 5 ) RDaddr_i [4:0] $end
$var wire 32 * RDdata_i [31:0] $end
$var wire 5 + RS1addr_i [4:0] $end
$var wire 5 , RS2addr_i [4:0] $end
$var wire 1 ' RegWrite_i $end
$var wire 1 ( clk_i $end
$var wire 32 - RS2data_o [31:0] $end
$var wire 32 . RS1data_o [31:0] $end
$var integer 32 / i [31:0] $end
$upscope $end
$upscope $end
$enddefinitions $end
$comment Show the parameter values. $end
$dumpall
$end
#0
$dumpvars
b100000 /
b0 .
b0 -
b0 ,
b0 +
b0 *
b0 )
0(
0'
b0 &
b0 %
b0 $
b0 #
b0 "
b0 !
$end
#5
1(
#10
0(
b11111111111111111111111111111111 $
b11111111111111111111111111111111 *
1'
#15
1(
#20
0(
0'
#25
1(
#30
0(
b10010001101000101011001111000 $
b10010001101000101011001111000 *
b1 #
b1 )
1'
#35
1(
#40
b10010001101000101011001111000 "
b10010001101000101011001111000 .
0(
0'
b1 %
b1 +
#45
1(
#50
0(
b10000111011001010100001100100001 $
b10000111011001010100001100100001 *
b10 #
b10 )
1'
#55
1(
#60
b10000111011001010100001100100001 !
b10000111011001010100001100100001 -
0(
0'
b10 &
b10 ,
#65
1(
#70
0(
b10101010101010101010101010101010 $
b10101010101010101010101010101010 *
b1 #
b1 )
#75
1(
#80
0(
#85
1(
#90
b0 "
b0 .
0(
b11 %
b11 +
b10111011101110111011101110111011 $
b10111011101110111011101110111011 *
b11 #
b11 )
1'
#95
b10111011101110111011101110111011 "
b10111011101110111011101110111011 .
1(
